kallithea_auth_container_internal/__init__.py
kallithea_auth_container_internal-2.0.dist-info/LICENSE
kallithea_auth_container_internal-2.0.dist-info/METADATA
kallithea_auth_container_internal-2.0.dist-info/WHEEL
kallithea_auth_container_internal-2.0.dist-info/top_level.txt
kallithea_auth_container_internal-2.0.dist-info/RECORD
