Metadata-Version: 2.1
Name: kallithea-auth-container-internal
Version: 2.0
Summary: Kallithea authentication plugin that accepts both container and internal authentication sources
Home-page: https://bitbucket.org/gclinch/kallithea-auth-container-internal
Author: Graham Clinch
Author-email: g.clinch@lancaster.ac.uk
License: Apache License, Version 2.0
Platform: UNKNOWN
Classifier: Development Status :: 5 - Production/Stable
Classifier: License :: OSI Approved :: Apache Software License
Classifier: Topic :: Software Development :: Version Control
License-File: LICENSE
